fxrates/__init__.py
fxrates/fxrates.py
fxrates-0.1.0.dist-info/LICENSE
fxrates-0.1.0.dist-info/METADATA
fxrates-0.1.0.dist-info/WHEEL
fxrates-0.1.0.dist-info/top_level.txt
fxrates-0.1.0.dist-info/RECORD
