Metadata-Version: 2.1
Name: fxrates
Version: 0.1.0
Summary: Python client to collect daily exchange rates provided by the ECB
Home-page: https://github.com/Etienne-larchet/fxrates
Author: Etienne LARCHET
License: MIT License
Classifier: License :: OSI Approved :: MIT License
Classifier: Programming Language :: Python :: 3
Classifier: Development Status :: 2 - Pre-Alpha
License-File: LICENSE
Requires-Dist: requests
Requires-Dist: pandas
